aio_net_events/__init__.py
aio_net_events/__main__.py
aio_net_events/py.typed
aio_net_events/task.py
aio_net_events/version.py
aio_net_events/backends/__init__.py
aio_net_events/backends/autodetect.py
aio_net_events/backends/base.py
aio_net_events/backends/macos.py
aio_net_events/backends/netlink.py
aio_net_events/backends/portable.py
aio_net_events-8.0.1.dist-info/METADATA
aio_net_events-8.0.1.dist-info/WHEEL
aio_net_events-8.0.1.dist-info/licenses/LICENSE
aio_net_events-8.0.1.dist-info/RECORD
