Metadata-Version: 2.4
Name: aio-net-events
Version: 8.0.1
Summary: Asynchronous network configuration event detector for Python 3.9 and above
Project-URL: Homepage, https://github.com/ntamas/aio-net-events/
Project-URL: Repository, https://github.com/ntamas/aio-net-events/
Author-email: Tamas Nepusz <tamas@collmot.com>
License-Expression: MIT
License-File: LICENSE
Requires-Python: >=3.9
Requires-Dist: anyio>=4.9.0
Requires-Dist: netifaces-plus>=0.12.2
Requires-Dist: pyobjc-core>=11.0; sys_platform == 'darwin'
Requires-Dist: pyobjc-framework-cocoa>=11.0; sys_platform == 'darwin'
Requires-Dist: pyobjc-framework-systemconfiguration>=11.0; sys_platform == 'darwin'
Provides-Extra: dev
Requires-Dist: coverage[toml]>=7.3.1; extra == 'dev'
Requires-Dist: pytest-cov>=6.1.1; extra == 'dev'
Requires-Dist: pytest>=8.0.0; extra == 'dev'
Requires-Dist: trio>=0.25; extra == 'dev'
